robust_python_demo/__init__.py
robust_python_demo/__main__.py
robust_python_demo/py.typed
robust_python_demo-0.33.0.dist-info/licenses/LICENSE
robust_python_demo-0.33.0.dist-info/METADATA
robust_python_demo-0.33.0.dist-info/WHEEL
robust_python_demo-0.33.0.dist-info/top_level.txt
robust_python_demo-0.33.0.dist-info/RECORD
