Metadata-Version: 2.4
Name: robust-python-demo
Version: 0.33.0
Summary: robust-python-demo
Author-email: Kyle Oliver <56kyleoliver+cookiecutter-robust-python@gmail.com>
License-Expression: MIT
Project-URL: Homepage, https://github.com/56kyle/robust-python-demo
Project-URL: Repository, https://github.com/56kyle/robust-python-demo
Keywords: robust-python-demo
Classifier: Operating System :: OS Independent
Classifier: Programming Language :: Python :: 3
Classifier: Programming Language :: Python :: 3 :: Only
Classifier: Programming Language :: Python :: 3.10
Classifier: Programming Language :: Python :: 3.11
Classifier: Programming Language :: Python :: 3.12
Classifier: Programming Language :: Python :: 3.13
Classifier: Programming Language :: Python :: 3.14
Classifier: Development Status :: 1 - Planning
Requires-Python: <4.0,>=3.10
License-File: LICENSE
Requires-Dist: loguru>=0.7.3
Requires-Dist: platformdirs>=4.3.8
Requires-Dist: typer>=0.15.4
Requires-Dist: typing-extensions>=4.13.2
Dynamic: license-file
